flora_tools/__init__.py
flora_tools/__main__.py
flora_tools/bench.py
flora_tools/experiment.py
flora_tools/gloria.py
flora_tools/gloria_flood.py
flora_tools/lwb_round.py
flora_tools/lwb_slot.py
flora_tools/lwb_visualizer.py
flora_tools/node.py
flora_tools/oscilloscope.py
flora_tools/radio_configuration.py
flora_tools/radio_math.py
flora_tools/utilities.py
flora_tools/experiments/__init__.py
flora_tools/experiments/measure_time_cad2done.py
flora_tools/experiments/measure_time_cad2rxdone.py
flora_tools/experiments/measure_time_cad2rxtimeout.py
flora_tools/experiments/measure_time_config.py
flora_tools/experiments/measure_time_get_payload.py
flora_tools/experiments/measure_time_get_pkt_status.py
flora_tools/experiments/measure_time_irq_process.py
flora_tools/experiments/measure_time_rx2rf.py
flora_tools/experiments/measure_time_rx2rxtimeout.py
flora_tools/experiments/measure_time_set_cad.py
flora_tools/experiments/measure_time_set_fs.py
flora_tools/experiments/measure_time_set_payload.py
flora_tools/experiments/measure_time_sleep_mode.py
flora_tools/experiments/measure_time_sniff_mode.py
flora_tools/experiments/measure_time_sweep_tx_rx.py
flora_tools/experiments/measure_time_sweep_tx_tx.py
flora_tools/experiments/measure_time_sync.py
flora_tools/experiments/measure_time_tx2rf.py
flora_tools/experiments/measure_time_tx2rxdone.py
flora_tools/experiments/measure_time_tx2rxdone_implicit.py
flora_tools/experiments/measure_time_tx2sync.py
flora_tools/experiments/measure_time_tx2txdone.py
flora_tools/experiments/measure_time_tx2txdone_implicit.py
flora_tools/experiments/test_simult_write_send.py
flora_tools/experiments/test_sniff_mode.py
flora_tools/sim/__init__.py
flora_tools/sim/lwb_schedule_manager.py
flora_tools/sim/sensor_service.py
flora_tools/sim/service.py
flora_tools/sim/sim_cad_scanner.py
flora_tools/sim/sim_cad_search.py
flora_tools/sim/sim_cad_sync.py
flora_tools/sim/sim_datastream_manager.py
flora_tools-0.1.11.dist-info/DESCRIPTION.rst
flora_tools-0.1.11.dist-info/METADATA
flora_tools-0.1.11.dist-info/RECORD
flora_tools-0.1.11.dist-info/WHEEL
flora_tools-0.1.11.dist-info/entry_points.txt
flora_tools-0.1.11.dist-info/metadata.json
flora_tools-0.1.11.dist-info/top_level.txt
