Metadata-Version: 2.0
Name: flora-tools
Version: 0.1.11
Summary: Tool and library for interfacing with the PermaSense Flora nodes, enabling programming, configuring and measuring.
Home-page: https://github.com/Atokulus/flora_tools.git
Author: atokulus
Author-email: atokulus@gmail.com
License: MIT
Platform: UNKNOWN
Classifier: Programming Language :: Python :: 3
Classifier: License :: OSI Approved :: MIT License
Classifier: Operating System :: OS Independent
Requires-Python: >=3.7
Requires-Dist: intelhex
Requires-Dist: jupyter
Requires-Dist: matplotlib
Requires-Dist: networkx
Requires-Dist: numpy
Requires-Dist: pandas
Requires-Dist: pyserial
Requires-Dist: pyvisa
Requires-Dist: setuptools
